IliasDownloaderUniMA/IliasDL.py
IliasDownloaderUniMA/__init__.py
IliasDownloaderUniMA-0.5.0.dist-info/LICENSE
IliasDownloaderUniMA-0.5.0.dist-info/METADATA
IliasDownloaderUniMA-0.5.0.dist-info/WHEEL
IliasDownloaderUniMA-0.5.0.dist-info/top_level.txt
IliasDownloaderUniMA-0.5.0.dist-info/RECORD
