Metadata-Version: 2.1
Name: IliasDownloaderUniMA
Version: 0.5.0
Summary: A simple package to download files from ilias.uni-mannheim.de
Home-page: UNKNOWN
Author: Jonathan Helgert
Author-email: jhelgert@mail.uni-mannheim.de
License: UNKNOWN
Platform: UNKNOWN
Classifier: Programming Language :: Python :: 3
Classifier: License :: OSI Approved :: MIT License
Classifier: Operating System :: OS Independent
Requires-Python: >=3.8
Requires-Dist: dateparser
Requires-Dist: bs4
Requires-Dist: requests
Requires-Dist: python-dateutil
Requires-Dist: lxml
